nd_okta_auth/__init__.py
nd_okta_auth/auth.py
nd_okta_auth/aws.py
nd_okta_auth/aws_saml.py
nd_okta_auth/base_client.py
nd_okta_auth/main.py
nd_okta_auth/metadata.py
nd_okta_auth/okta.py
nd_okta_auth/factor/__init__.py
nd_okta_auth/factor/push.py
nd_okta_auth/factor/totp.py
nd_okta_auth/factor/u2f.py
nd_okta_auth/factor/webauthn.py
nd_okta_auth-1.0.6.dist-info/METADATA
nd_okta_auth-1.0.6.dist-info/WHEEL
nd_okta_auth-1.0.6.dist-info/entry_points.txt
nd_okta_auth-1.0.6.dist-info/top_level.txt
nd_okta_auth-1.0.6.dist-info/RECORD
