Metadata-Version: 2.1
Name: nd-okta-auth
Version: 1.0.6
Summary: Nextdoor Okta Auther
Home-page: https://github.com/Nextdoor/nd_okta_auth
Download-URL: http://pypi.python.org/pypi/nd_okta_auth#downloads
Author: Nextdoor Engineering
Author-email: eng@nextdoor.com
License: Apache License, Version 2.0
Keywords: apache
Classifier: Development Status :: 4 - Beta
Classifier: Topic :: Software Development
Classifier: License :: OSI Approved :: Apache Software License
Classifier: Intended Audience :: Developers
Classifier: Programming Language :: Python
Classifier: Operating System :: POSIX
Classifier: Natural Language :: English
Requires-Dist: bs4 (>=0.0.1)
Requires-Dist: rainbow-logging-handler (>=2.2.2)
Requires-Dist: requests (>=2.10.0)
Requires-Dist: boto3 (>=1.4.0)
Requires-Dist: future (==0.18.3)
Requires-Dist: configparser (==3.5.0)
Requires-Dist: fido2 (==0.8.1)
